ibatch/__init__.py
ibatch/main.py
ibatch/photo.py
ibatch-0.2.0.dist-info/licenses/LICENSE
ibatch-0.2.0.dist-info/WHEEL
ibatch-0.2.0.dist-info/entry_points.txt
ibatch-0.2.0.dist-info/METADATA
ibatch-0.2.0.dist-info/RECORD
