Metadata-Version: 2.4
Name: ibatch
Version: 0.2.0
Summary: 
Author: David Polák
Author-email: David Polák <email@davidpolak.cz>
License-Expression: GPL-3.0-or-later
License-File: LICENSE
Classifier: Programming Language :: Python :: 3.13
Classifier: Programming Language :: Python :: 3.14
Requires-Dist: click>=8.3.1
Requires-Dist: geopy>=2.4.1
Requires-Dist: pyexiftool>=0.5.6
Requires-Python: >=3.13, <4
